starburst/__init__.py
starburst/choice.py
starburst/conic.py
starburst/cornea.py
starburst/main.py
starburst/ransac.py
starburst/refine.py
starburst/starburst.py
starburst/utils.py
starburst-0.1.0.dist-info/LICENSE.txt
starburst-0.1.0.dist-info/METADATA
starburst-0.1.0.dist-info/WHEEL
starburst-0.1.0.dist-info/entry_points.txt
starburst-0.1.0.dist-info/top_level.txt
starburst-0.1.0.dist-info/RECORD
