Metadata-Version: 2.1
Name: starburst
Version: 0.1.0
Summary: identify and measure pupil using starburst algorithm
Home-page: https://github.com/Palpatineli/starburst
Author: Keji Li
Author-email: mail@keji.li
License: GPLv3
Download-URL: https://github.com/Palpatineli/starburst/archive/0.1.0.tar.gz
Platform: UNKNOWN
Classifier: Development Status :: 4 - Beta
Classifier: Programming Language :: Python :: 3
Requires-Dist: numpy
Requires-Dist: opencv-python (>=3.0)
Requires-Dist: scipy
Requires-Dist: tiffreader
Requires-Dist: tqdm
Requires-Dist: uifunc
